vpetabc/__init__.py
vpetabc/engine.py
vpetabc/models.py
vpetabc/priors.py
vpetabc/utilities.py
vpet_abc-0.1.3.dist-info/METADATA
vpet_abc-0.1.3.dist-info/WHEEL
vpet_abc-0.1.3.dist-info/licenses/LICENSE
vpet_abc-0.1.3.dist-info/RECORD
