Metadata-Version: 2.4
Name: vpet-abc
Version: 0.1.3
Summary: Fast likelihood-free PET kinetic modelling in JAX
Project-URL: Homepage, https://github.com/zephyralistair/vPET-ABC-fast-PET-kinetic-modelling-on-large-data
Author-email: Qinlin Gu <qinlin@sydney.edu.au>
License: MIT
License-File: LICENSE
Requires-Python: >=3.9.2
Requires-Dist: jax>=0.4.30
Requires-Dist: pandas>=2.2.3
Requires-Dist: tqdm>=4.67.1
Provides-Extra: cuda
Requires-Dist: jax[cuda]; extra == 'cuda'
